{"cameraMode":{"drawMode":0,"name":"Shaded","section":"Shading Mode"},"sceneLighting":true,"audioPlay":false,"sceneViewState":{"m_AlwaysRefresh":false,"showFog":true,"showSkybox":true,"showFlares":true,"showImageEffects":true,"showParticleSystems":true,"showVisualEffectGraphs":true,"m_FxEnabled":true},"in2DMode":false,"pivot":{"x":-0.9547179937362671,"y":4.499166965484619,"z":-0.30244994163513186},"rotation":{"x":0.027273522689938546,"y":-0.7091070413589478,"z":0.027456004172563554,"w":0.7040292024612427},"size":7.989625930786133,"orthographic":false}